rethinkdb_pandas/__init__.py
rethinkdb_pandas/core/__init__.py
rethinkdb_pandas/core/db.py
rethinkdb_pandas/core/rethinkdb.py
rethinkdb_pandas/core/table.py
rethinkdb_pandas-0.0.1.dist-info/LICENSE
rethinkdb_pandas-0.0.1.dist-info/WHEEL
rethinkdb_pandas-0.0.1.dist-info/METADATA
rethinkdb_pandas-0.0.1.dist-info/RECORD
