Metadata-Version: 2.1
Name: rethinkdb-pandas
Version: 0.0.1
Summary: Unofficial Python driver library for the RethinkDB database server with Pandas
Author-email: somehitDev <this.dev.somehit@gmail.com>
Requires-Python: >=3.9
Classifier: License :: OSI Approved :: Apache Software License
Classifier: Operating System :: MacOS :: MacOS X
Classifier: Operating System :: POSIX
Classifier: Operating System :: Microsoft :: Windows
Classifier: Programming Language :: Python :: 3
Classifier: Programming Language :: Python :: 3.9
Classifier: Programming Language :: Python :: 3.10
Classifier: Programming Language :: Python :: 3.11
Classifier: Topic :: Database
Classifier: Topic :: Utilities
Requires-Dist: rethinkdb==2.4.10.post1
Requires-Dist: pandas==2.2.2
Project-URL: Home, https://github.com/somehitDev/rethinkdb_pandas
